{
  "recipe": [
    {
      "id": 0,
      "name": "Nudeln mit Tomatensoße",
      "time": 30,
      "persons": 4,
      "level": 1,
      "rating": 5,
      "user": 0,
      "ingredients": [
        {
          "id": 0,
          "name": "Nudeln",
          "amount": 500,
          "unit": "g"
        },
        {
          "id": 1,
          "name": "passierte Tomaten",
          "amount": 500,
          "unit": "g"
        },
        {
          "id": 2,
          "name": "Zwiebeln",
          "amount": 2
        },
        {
          "id": 3,
          "name": "Knoblauch",
          "amount": 2,
          "unit": "Zehen"
        },
        {
          "id": 4,
          "name": "Öl"
        },
        {
          "id": 5,
          "name": "Gewürze"
        }
      ],
      "preparation": [
        "Nudeln wie auf Packung kochen",
        "Zwiebel und Knoblauch in kleine Würfel schneiden",
        "Öl in eine Pfanne erhitzen",
        "Zwiebel auf mittlere Temperatur für ca. 5 min anbraten",
        "Knoblauch in die Pfanne geben und weitere 2 min anbraten",
        "die passierten Tomaten dazugeben und kurz köcheln lassen",
        "die Soße mit Salz, Pfeffer und Chilie abschmecken",
        "Fertig"
      ]
    },
    {
      "id": 1,
      "name": "Heiße Milch",
      "time": "4",
      "persons": 1,
      "level": 1,
      "rating": 5,
      "user": 0,
      "ingredients": [
        {
          "id": 0,
          "name": "Milch",
          "amount": 200,
          "unit": "ml"
        },
        {
          "id": 1,
          "name": "Honig",
          "amount": 1,
          "unit": "Löffel"
        }
      ],
      "preparation": [
        "Milch erwärmen",
        "mit Honiglöffel umrühren",
        "Genießen"
      ]
    },
    {
      "id": 2,
      "name": "Bier",
      "time": "30241",
      "persons": "20",
      "level": 2,
      "rating": 5,
      "user": 0,
      "ingredients": [
        {
          "id": 0,
          "name": "Wasser",
          "amount": 33,
          "unit": "l"
        },
        {
          "id": 1,
          "name": "Pilsner Malz",
          "amount": 4.25,
          "unit": "kg"
        },
        {
          "id": 2,
          "name": "Maisflocken",
          "amount": 1,
          "unit": "kg"
        },
        {
          "id": 3,
          "name": "Lotus, ",
          "amount": 20,
          "unit": "g"
        },
        {
          "id": 4,
          "name": "Trockenhefe(Fermentis SafAle K-97)"
        }
      ],
      "preparation": [
        "MAISCHPLAN",
        "Einmaischen bei 65 °C",
        "Kombirast bei 65 °C für 60 min, wenn Jodnormal weiter zu",
        "Abmaischen 78 °C für 1 min",
        "HOPFENGABEN",
        "Lotus 5g bei 60 min",
        "Lotus 15g bei 5 min"
      ]
    },
    {
      "name": "Reis",
      "time": "16",
      "level": "1",
      "persons": 4,
      "rating": "4",
      "user": 1,
      "ingredients": [
        {
          "id": 0,
          "name": "Reis",
          "amount": "500",
          "unit": "g"
        },
        {
          "id": 1,
          "name": "Wasser",
          "amount": "1",
          "unit": "l"
        }
      ],
      "preparation": [
        "Resi und wasser in einen Topf geben und 15 min köcheln lassen.",
        " Wenn das Wasser verkocht ist, ist der Reis fertig!"
      ],
      "id": 3
    },
    {
      "name": "Käse Lauch Suppe",
      "time": "31",
      "persons": 4,
      "level": 1,
      "rating": "5",
      "user": 2,
      "ingredients": [
        {
          "id": 0,
          "name": "Hackfleisch",
          "amount": "500",
          "unit": "g"
        },
        {
          "id": 1,
          "name": "Lauch",
          "amount": "3",
          "unit": "Stangen"
        },
        {
          "id": 2,
          "name": "Schmelzkäse",
          "amount": "250",
          "unit": "g"
        },
        {
          "id": 3,
          "name": "Brühe",
          "amount": "500",
          "unit": "ml"
        },
        {
          "id": 4,
          "name": "Knoblauch",
          "amount": "5",
          "unit": "Zehen"
        },
        {
          "id": 5,
          "name": "Schmand",
          "amount": "200",
          "unit": "g"
        }
      ],
      "preparation": [
        "Hackfleisch, zwieben, knoblauch und lauch anbraten",
        "Brühe, Käse und den Schmand Dazugeben",
        "5 min köcheln lassen",
        "Abschmecken und Fertig!"
      ],
      "id": 4
    },
    {
      "name": "Nudeln mit aglio e olio",
      "time": "20",
      "level": 1,
      "rating": "5",
      "user": 0,
      "persons": "4",
      "ingredients": [
        {
          "id": 0,
          "name": "Nudeln",
          "amount": "400",
          "unit": "g"
        },
        {
          "id": 1,
          "name": "Knoblauch",
          "amount": "4",
          "unit": "Zehen"
        },
        {
          "id": 2,
          "name": "Öl",
          "amount": "150",
          "unit": "ml"
        }
      ],
      "preparation": [
        "Die Spaghetti in einem großen Topf in reichlich Salzwasser al dente (ca. 8 Minuten) kochen",
        "Die Knoblauchzehen schälen, durch die Knoblauchpresse drücken oder fein hacken. Die Petersilie waschen, trockenschwenken und die Blätter fein hacken.",
        " In einer Pfanne das Olivenöl mit Knoblauch, Petersilie und Pfefferoni bei schwacher Hitze erwärmen, etwa 3 Min. ziehen lassen. Nach Belieben salzen.",
        " Die Nudeln in ein Sieb schütten, gut abtropfen lassen, in die Pfanne zum Knoblauchöl hinzugeben und gut durchmischen."
      ],
      "id": 5
    }
  ],
  "user": [
    {
      "name": "admin",
      "username": "admin",
      "password": "admin",
      "email": "admin@admin.de",
      "id": 0,
      "favorites": [
        4,
        2,
        1,
        0,
        3
      ],
      "shoppingList": [
        {
          "recipe": 0,
          "amount": 8,
          "checked": [
            true,
            true,
            true,
            true,
            true,
            true
          ],
          "allChecked": true
        }
      ]
    },
    {
      "name": "Lucas",
      "username": "luc",
      "password": "as",
      "email": "lucas@lucas.de",
      "id": 1,
      "favorites": [
        1,
        2,
        3,
        4
      ],
      "shoppingList": []
    },
    {
      "name": "Fenja",
      "username": "fen",
      "password": "ja",
      "email": "fenja@fenja.de",
      "id": 2,
      "favorites": [
        1,
        4
      ],
      "shoppingList": []
    },
    {
      "name": "test",
      "username": "test",
      "email": "test@test.test",
      "password": "test",
      "id": 3,
      "favorites": [
        0
      ],
      "shoppingList": [
        {
          "recipe": 1,
          "amount": 123,
          "checked": [
            true,
            true
          ],
          "allChecked": true
        },
        {
          "recipe": 0,
          "amount": 52,
          "checked": [
            true,
            true,
            true,
            true,
            true,
            true
          ],
          "allChecked": true
        }
      ]
    }
  ]
}